sshfs_offline/__init__.py
sshfs_offline/cli.py
sshfs_offline/color.py
sshfs_offline/common.py
sshfs_offline/commonfunc.py
sshfs_offline/config.py
sshfs_offline/data.py
sshfs_offline/db.py
sshfs_offline/directories.py
sshfs_offline/eventq.py
sshfs_offline/filesystem.py
sshfs_offline/gitignore.py
sshfs_offline/localonly.py
sshfs_offline/lock.py
sshfs_offline/log.py
sshfs_offline/mem.py
sshfs_offline/metadata.py
sshfs_offline/metrics.py
sshfs_offline/stats.py
sshfs_offline/remote/attr.py
sshfs_offline/remote/attrnew.py
sshfs_offline/remote/chmod.py
sshfs_offline/remote/chown.py
sshfs_offline/remote/cnn.py
sshfs_offline/remote/create.py
sshfs_offline/remote/getxattr.py
sshfs_offline/remote/mkdir.py
sshfs_offline/remote/readdir.py
sshfs_offline/remote/readlink.py
sshfs_offline/remote/remove.py
sshfs_offline/remote/rename.py
sshfs_offline/remote/rmdir.py
sshfs_offline/remote/symlink.py
sshfs_offline/remote/truncate.py
sshfs_offline/remote/utime.py
sshfs_offline/threads/heartbeat.py
sshfs_offline/threads/refresh.py
sshfs_offline/threads/refreshcache.py
sshfs_offline/threads/rpc.py
sshfs_offline/threads/tcreate.py
sshfs_offline/threads/tdelete.py
sshfs_offline/threads/tdownload.py
sshfs_offline/threads/tupload.py
sshfs_offline-0.0.9.dist-info/licenses/LICENSE
sshfs_offline-0.0.9.dist-info/METADATA
sshfs_offline-0.0.9.dist-info/WHEEL
sshfs_offline-0.0.9.dist-info/entry_points.txt
sshfs_offline-0.0.9.dist-info/top_level.txt
sshfs_offline-0.0.9.dist-info/RECORD
