Metadata-Version: 2.4
Name: sshfs-offline
Version: 0.0.9
Summary: SSH File System with offline access to cached files.
Author-email: Dave Christenson <davechri58@gmail.com>
License: MIT
Project-URL: Repository, https://github.com/davechri/sshfs-offline
Project-URL: Issues, https://github.com/davechri/sshfs-offline/issues
Keywords: offline,cache,sshfs,fuse-filesystem,fuse
Classifier: Development Status :: 4 - Beta
Classifier: Topic :: System :: Filesystems
Classifier: Development Status :: 4 - Beta
Classifier: Intended Audience :: Developers
Classifier: Intended Audience :: End Users/Desktop
Classifier: Operating System :: MacOS :: MacOS X
Classifier: Operating System :: POSIX :: Linux
Classifier: Programming Language :: Python
Classifier: Programming Language :: Python :: 2.7
Classifier: Programming Language :: Python :: 3.3
Classifier: Programming Language :: Python :: 3.4
Classifier: Programming Language :: Python :: 3.5
Classifier: Programming Language :: Python :: Implementation :: PyPy
Classifier: License :: OSI Approved :: MIT License
License-File: LICENSE
Requires-Dist: fusepy==3.0.1
Requires-Dist: paramiko==4.0.0
Requires-Dist: plyvel==1.5.1
Requires-Dist: gitignore_parser==0.1.13
Requires-Dist: humanize==4.15.0
Dynamic: license-file
